ptame/__init__.py
ptame/ax_sweep.py
ptame/print_map.py
ptame/train.py
ptame/configs/__init__.py
ptame/data/__init__.py
ptame/data/imagenet_datamodule.py
ptame/data/components/__init__.py
ptame/datalists/__init__.py
ptame/models/__init__.py
ptame/models/cv_module.py
ptame/models/ptame_module.py
ptame/models/components/__init__.py
ptame/models/components/loss.py
ptame/models/components/ptame_pipeline.py
ptame/models/components/rand_model.py
ptame/models/components/ttame.py
ptame/models/components/attention/__init__.py
ptame/models/components/attention/ptame_attention.py
ptame/models/components/attention/ttame_attention.py
ptame/models/components/hooks/__init__.py
ptame/utils/__init__.py
ptame/utils/instantiators.py
ptame/utils/logging_utils.py
ptame/utils/map_printer.py
ptame/utils/masking_utils.py
ptame/utils/measures.py
ptame/utils/memory_format.py
ptame/utils/noisy_linear_imputation.py
ptame/utils/pylogger.py
ptame/utils/rich_utils.py
ptame/utils/utils.py
ptame-1.0.2.dist-info/licenses/LICENSE
ptame-1.0.2.dist-info/METADATA
ptame-1.0.2.dist-info/WHEEL
ptame-1.0.2.dist-info/entry_points.txt
ptame-1.0.2.dist-info/top_level.txt
ptame-1.0.2.dist-info/RECORD
