Metadata-Version: 2.4
Name: ptame
Version: 1.0.2
Summary: Explain Any Image Classifier with Trained Perturbations
Author-email: "Mariano V. Ntrougkas" <ntrougkas@iti.gr>
License-Expression: LicenseRef-Custom-Academic-NonCommercial
Project-URL: homepage, https://github.com/IDT-ITI/P-TAME
Project-URL: source, https://github.com/IDT-ITI/P-TAME.git
Project-URL: documentation, https://idt-iti.github.io/P-TAME/ptame.html
Project-URL: issues, https://github.com/IDT-ITI/P-TAME/issues
Requires-Python: >=3.10
License-File: LICENSE
Requires-Dist: lightning
Requires-Dist: hydra-core
Requires-Dist: torch
Requires-Dist: torchvision
Requires-Dist: torchmetrics
Requires-Dist: opencv-python-headless
Requires-Dist: numpy
Requires-Dist: pandas
Requires-Dist: ax-platform
Requires-Dist: hydra-colorlog
Requires-Dist: rich
Requires-Dist: importlib_resources
Requires-Dist: torchshow
Provides-Extra: dev
Requires-Dist: wandb; extra == "dev"
Requires-Dist: pre-commit; extra == "dev"
Requires-Dist: pdoc; extra == "dev"
Requires-Dist: seaborn; extra == "dev"
Requires-Dist: scipy; extra == "dev"
Dynamic: license-file
